sdk/client.py
sdk/collection.py
sdk/film.py
sdk/film_collection.py
sdk/film_tag.py
sdk/people.py
sdk/people_collection.py
sdk/people_tag.py
sdk/planet.py
sdk/planet_collection.py
sdk/planet_tag.py
sdk/root.py
sdk/species.py
sdk/species_collection.py
sdk/species_tag.py
sdk/starship.py
sdk/starship_collection.py
sdk/starship_tag.py
sdk/vehicle.py
sdk/vehicle_collection.py
sdk/vehicle_tag.py
sdkfabric_starwars-0.1.8.dist-info/LICENSE
sdkfabric_starwars-0.1.8.dist-info/METADATA
sdkfabric_starwars-0.1.8.dist-info/WHEEL
sdkfabric_starwars-0.1.8.dist-info/top_level.txt
sdkfabric_starwars-0.1.8.dist-info/RECORD
