Metadata-Version: 2.2
Name: sdkfabric-starwars
Version: 0.1.8
Summary: Starwars Python SDK managed by SDK Fabric
Author-email: Christoph Kappestein <christoph.kappestein@gmail.com>
License: MIT
Project-URL: Homepage, https://github.com/sdk-fabric/starwars-python
Project-URL: Issues, https://github.com/sdk-fabric/starwars-python/issues
Classifier: Programming Language :: Python :: 3
Classifier: License :: OSI Approved :: MIT License
Classifier: Operating System :: OS Independent
Classifier: Topic :: Software Development :: Code Generators
Requires-Python: >=3.8
License-File: LICENSE
Requires-Dist: sdkgen-client
